{
  "id": "da39a3ee5e6b4b0d3255bfef95601890afd80709",
  "messageType": "Avro",
  "dataSetWriters": [
    {
      "dataSetWriterId": 0,
      "id": "cb0a88f5c176801edf4154608ec5abd8b6bab607",
      "dataSetWriterName": null,
      "dataSet": {
        "name": "PendingAlarms",
        "dataSetSource": {
          "connection": {
            "endpoint": {
              "url": "opc.tcp://localhost:61457/UA/SampleServer",
              "securityMode": "Best"
            }
          },
          "subscriptionSettings": {},
          "publishedEvents": {
            "publishedData": [
              {
                "id": "d920882831d06cc8d35e34b3911064367b9b7ced",
                "eventNotifier": "i=2253",
                "selectedFields": [
                  {
                    "typeDefinitionId": "i=2041",
                    "browsePath": [
                      "ConditionClassId"
                    ],
                    "attributeId": "Value",
                    "dataSetFieldName": "ConditionClassId",
                    "dataSetClassFieldId": "a7430280-8c48-409d-aaf5-17df87c20dd4",
                    "metaData": {
                      "minorVersion": 1,
                      "builtInType": 17,
                      "dataType": "i=17",
                      "valueRank": -1
                    }
                  },
                  {
                    "typeDefinitionId": "i=2041",
                    "browsePath": [
                      "ConditionClassName"
                    ],
                    "attributeId": "Value",
                    "dataSetFieldName": "ConditionClassName",
                    "dataSetClassFieldId": "a0ee31bd-0cba-42d1-bfcc-ef9363ca6e76",
                    "metaData": {
                      "minorVersion": 1,
                      "builtInType": 21,
                      "dataType": "i=21",
                      "valueRank": -1
                    },
                    "fieldIndex": 1
                  },
                  {
                    "typeDefinitionId": "i=2041",
                    "browsePath": [
                      "ConditionSubClassId"
                    ],
                    "attributeId": "Value",
                    "dataSetFieldName": "ConditionSubClassId",
                    "dataSetClassFieldId": "3e527a99-c887-4000-aa65-1126bc48d64c",
                    "metaData": {
                      "minorVersion": 1,
                      "builtInType": 17,
                      "dataType": "i=17",
                      "valueRank": 1,
                      "arrayDimensions": [
                        0
                      ]
                    },
                    "fieldIndex": 2
                  },
                  {
                    "typeDefinitionId": "i=2041",
                    "browsePath": [
                      "ConditionSubClassName"
                    ],
                    "attributeId": "Value",
                    "dataSetFieldName": "ConditionSubClassName",
                    "dataSetClassFieldId": "90ed8f86-9e6d-48b8-9e87-afd3067c1b66",
                    "metaData": {
                      "minorVersion": 1,
                      "builtInType": 21,
                      "dataType": "i=21",
                      "valueRank": 1,
                      "arrayDimensions": [
                        0
                      ]
                    },
                    "fieldIndex": 3
                  },
                  {
                    "typeDefinitionId": "i=2041",
                    "browsePath": [
                      "EventId"
                    ],
                    "attributeId": "Value",
                    "dataSetFieldName": "EventId",
                    "dataSetClassFieldId": "32717bf3-0582-4ea5-a976-eea69e289a5d",
                    "metaData": {
                      "minorVersion": 1,
                      "builtInType": 15,
                      "dataType": "i=15",
                      "valueRank": -1
                    },
                    "fieldIndex": 4
                  },
                  {
                    "typeDefinitionId": "i=2041",
                    "browsePath": [
                      "EventType"
                    ],
                    "attributeId": "Value",
                    "dataSetFieldName": "EventType",
                    "dataSetClassFieldId": "6de4325f-a2b5-4e12-9db8-d4a96dfef8a9",
                    "metaData": {
                      "minorVersion": 1,
                      "builtInType": 17,
                      "dataType": "i=17",
                      "valueRank": -1
                    },
                    "fieldIndex": 5
                  },
                  {
                    "typeDefinitionId": "i=2041",
                    "browsePath": [
                      "LocalTime"
                    ],
                    "attributeId": "Value",
                    "dataSetFieldName": "LocalTime",
                    "dataSetClassFieldId": "9c7a438e-5844-498e-bde5-ee028e3b1295",
                    "metaData": {
                      "minorVersion": 1,
                      "builtInType": 22,
                      "dataType": "i=8912",
                      "valueRank": -1,
                      "StructureDataTypes": [
                        {
                          "DataTypeId": "i=8912",
                          "Name": "TimeZoneDataType",
                          "StructureType": "Structure",
                          "Fields": [
                            {
                              "name": "Offset",
                              "dataType": "i=4",
                              "valueRank": -1,
                              "arrayDimensions": []
                            },
                            {
                              "name": "DaylightSavingInOffset",
                              "dataType": "i=1",
                              "valueRank": -1,
                              "arrayDimensions": []
                            }
                          ],
                          "BaseDataType": "i=22",
                          "DefaultEncodingId": "i=8917"
                        }
                      ],
                      "enumDataTypes": [],
                      "simpleDataTypes": []
                    },
                    "fieldIndex": 6
                  },
                  {
                    "typeDefinitionId": "i=2041",
                    "browsePath": [
                      "Message"
                    ],
                    "attributeId": "Value",
                    "dataSetFieldName": "Message",
                    "dataSetClassFieldId": "f345766b-7b17-4007-8cd4-301b0e8a1992",
                    "metaData": {
                      "minorVersion": 1,
                      "builtInType": 21,
                      "dataType": "i=21",
                      "valueRank": -1
                    },
                    "fieldIndex": 7
                  },
                  {
                    "typeDefinitionId": "i=2041",
                    "browsePath": [
                      "ReceiveTime"
                    ],
                    "attributeId": "Value",
                    "dataSetFieldName": "ReceiveTime",
                    "dataSetClassFieldId": "28e6e412-0c57-4cdd-a0db-9fbd88c106d6",
                    "metaData": {
                      "minorVersion": 1,
                      "builtInType": 13,
                      "dataType": "i=294",
                      "valueRank": -1,
                      "StructureDataTypes": [],
                      "enumDataTypes": [],
                      "simpleDataTypes": [
                        {
                          "dataTypeId": "i=294",
                          "name": "UtcTime",
                          "baseDataType": "i=13",
                          "builtInType": 13
                        }
                      ]
                    },
                    "fieldIndex": 8
                  },
                  {
                    "typeDefinitionId": "i=2041",
                    "browsePath": [
                      "Severity"
                    ],
                    "attributeId": "Value",
                    "dataSetFieldName": "Severity",
                    "dataSetClassFieldId": "b2c409c2-3efc-48ea-84ee-a9ba518eaf46",
                    "metaData": {
                      "minorVersion": 1,
                      "builtInType": 5,
                      "dataType": "i=5",
                      "valueRank": -1
                    },
                    "fieldIndex": 9
                  },
                  {
                    "typeDefinitionId": "i=2041",
                    "browsePath": [
                      "SourceName"
                    ],
                    "attributeId": "Value",
                    "dataSetFieldName": "SourceName",
                    "dataSetClassFieldId": "3ac7c494-99a6-41fc-902b-22f971264034",
                    "metaData": {
                      "minorVersion": 1,
                      "builtInType": 12,
                      "dataType": "i=12",
                      "valueRank": -1
                    },
                    "fieldIndex": 10
                  },
                  {
                    "typeDefinitionId": "i=2041",
                    "browsePath": [
                      "SourceNode"
                    ],
                    "attributeId": "Value",
                    "dataSetFieldName": "SourceNode",
                    "dataSetClassFieldId": "b6a034bd-5a30-4bb7-8621-70fdc7ca46d5",
                    "metaData": {
                      "minorVersion": 1,
                      "builtInType": 17,
                      "dataType": "i=17",
                      "valueRank": -1
                    },
                    "fieldIndex": 11
                  },
                  {
                    "typeDefinitionId": "i=2041",
                    "browsePath": [
                      "Time"
                    ],
                    "attributeId": "Value",
                    "dataSetFieldName": "Time",
                    "dataSetClassFieldId": "86d0b9e9-c10f-4e35-a66a-dab12ce993be",
                    "metaData": {
                      "minorVersion": 1,
                      "builtInType": 13,
                      "dataType": "i=294",
                      "valueRank": -1,
                      "StructureDataTypes": [],
                      "enumDataTypes": [],
                      "simpleDataTypes": [
                        {
                          "dataTypeId": "i=294",
                          "name": "UtcTime",
                          "baseDataType": "i=13",
                          "builtInType": 13
                        }
                      ]
                    },
                    "fieldIndex": 12
                  }
                ],
                "filter": {
                  "elements": [
                    {
                      "filterOperator": "OfType",
                      "filterOperands": [
                        {
                          "value": "i=2041"
                        }
                      ]
                    }
                  ]
                },
                "conditionHandling": {
                  "updateInterval": 10,
                  "snapshotInterval": 20
                },
                "typeDefinitionId": null,
                "name": "PendingAlarms"
              }
            ]
          }
        },
        "dataSetMetaData": {
          "majorVersion": 1
        },
        "sendKeepAlive": false,
        "Routing": "None"
      },
      "dataSetFieldContentMask": "StatusCode, SourceTimestamp, ServerTimestamp, NodeId, DisplayName, EndpointUrl, ApplicationUri, ExtensionFields",
      "messageSettings": {
        "dataSetMessageContentMask": "Timestamp, MetaDataVersion, DataSetWriterId, MajorVersion, MinorVersion, SequenceNumber, MessageType, DataSetWriterName"
      },
      "metaData": {
        "queueName": "PendingAlarms/<<UnknownWriterGroup>>"
      },
      "publishing": {
        "queueName": "PendingAlarms/<<UnknownWriterGroup>>"
      }
    }
  ],
  "messageSettings": {
    "networkMessageContentMask": "PublisherId, WriterGroupId, NetworkMessageNumber, SequenceNumber, PayloadHeader, Timestamp, DataSetClassId, NetworkMessageHeader, DataSetMessageHeader",
    "groupVersion": 1,
    "namespaceFormat": "Expanded"
  }
}